handsome/__init__.py
handsome/boy/__init__.py
handsome/boy/message.py
Lgy-0.1.dist-info/METADATA
Lgy-0.1.dist-info/WHEEL
Lgy-0.1.dist-info/top_level.txt
Lgy-0.1.dist-info/RECORD
