Metadata-Version: 2.1
Name: Lgy
Version: 0.1
Summary: 蔺广域
Author: Lgy
License: UNKNOWN
Platform: UNKNOWN
